[


    {
        "name":"c bhanuprakash",
        "pinnumber":"20101-cm-003",
        "firstpayment":"paid",
        "secondpayment":"paid",
        "thirdpayment":"unpaid",
        "amount":"4700/-",
        "photo":"/private/imagecme/cm003.png",
        "branch":"dcme",
        "phonenumber":"9786523412"
    },
    {
        "name":"M ajay kumar",
        "pinnumber":"20101-cm-001",
        "firstpayment":"paid",
        "secondpayment":"paid",
        "thirdpayment":"unpaid",
        "amount":"4700/-",
        "photo":"/private/imagecme/cm001.jpg",
        "branch":"dcme",
        "phonenumber":"9786523412"
    },
    {
        "name":"A dileep",
        "pinnumber":"20101-cm-004",
        "firstpayment":"paid",
        "secondpayment":"paid",
        "thirdpayment":"unpaid",
        "amount":"4700/-",
        "photo":"/private/imagecme/cm004.jpg",
        "branch":"dcme",
        "phonenumber":"9786523412"
    },
    {
        "name":"S hemasree",
        "pinnumber":"20101-cm-008",
        "firstpayment":"paid",
        "secondpayment":"paid",
        "thirdpayment":"unpaid",
        "amount":"4700/-",
        "photo":"/private/imagecme/cm008.jpg",
        "branch":"dcme",
        "phonenumber":"9786523412"
    },
    {
        "name":"V pavani",
        "pinnumber":"20101-cm-010",
        "firstpayment":"paid",
        "secondpayment":"paid",
        "thirdpayment":"unpaid",
        "amount":"4700/-",
        "photo":"/private/imagecme/cm010.jpg",
        "branch":"dcme",
        "phonenumber":"9786523412"
    },
    {
        "name":"M kiran kumar",
        "pinnumber":"20101-cm-011",
        "firstpayment":"paid",
        "secondpayment":"paid",
        "thirdpayment":"unpaid",
        "amount":"4700/-",
        "photo":"/private/imagecme/cm011.jpg",
        "branch":"dcme",
        "phonenumber":"9786523412"
    },
    {
        "name":"M mahammad shami",
        "pinnumber":"20101-cm-004",
        "firstpayment":"paid",
        "secondpayment":"paid",
        "thirdpayment":"unpaid",
        "amount":"4700/-",
        "photo":"/private/imagecme/cm012.jpg",
        "branch":"dcme",
        "phonenumber":"9786523412"
    },
    {
        "name":"B mahesh",
        "pinnumber":"20101-cm-013",
        "firstpayment":"paid",
        "secondpayment":"paid",
        "thirdpayment":"unpaid",
        "amount":"4700/-",
        "photo":"/private/imagecme/cm013.jpg",
        "branch":"dcme",
        "phonenumber":"9786523412"
    },
    {
        "name":"B nandakishore",
        "pinnumber":"20101-cm-014",
        "firstpayment":"paid",
        "secondpayment":"paid",
        "thirdpayment":"unpaid",
        "amount":"4700/-",
        "photo":"/private/imagecme/cm014.jpg",
        "branch":"dcme",
        "phonenumber":"9786523412"
    },
    {
        "name":"V pavan",
        "pinnumber":"20101-cm-015",
        "firstpayment":"paid",
        "secondpayment":"paid",
        "thirdpayment":"unpaid",
        "amount":"4700/-",
        "photo":"/private/imagecme/cm015.jpg",
        "branch":"dcme",
        "phonenumber":"9786523412"
    },
    {
        "name":"S keerthiveni",
        "pinnumber":"20101-cm-016",
        "firstpayment":"paid",
        "secondpayment":"paid",
        "thirdpayment":"unpaid",
        "amount":"4700/-",
        "photo":"/private/imagecme/cm016.jpg",
        "branch":"dcme",
        "phonenumber":"9786523412"
    },
    {
        "name":"E rammohn",
        "pinnumber":"20101-cm-017",
        "firstpayment":"paid",
        "secondpayment":"paid",
        "thirdpayment":"unpaid",
        "amount":"4700/-",
        "photo":"/private/imagecme/cm017.jpg",
        "branch":"dcme",
        "phonenumber":"9786523412"
    },
    {
        "name":"C ramakrishna",
        "pinnumber":"20101-cm-018",
        "firstpayment":"paid",
        "secondpayment":"paid",
        "thirdpayment":"unpaid",
        "amount":"4700/-",
        "photo":"/private/imagecme/cm018.jpg",
        "branch":"dcme",
        "phonenumber":"9786523412"
    },
    {
        "name":"S satyapriya",
        "pinnumber":"20101-cm-020",
        "firstpayment":"paid",
        "secondpayment":"paid",
        "thirdpayment":"unpaid",
        "amount":"4700/-",
        "photo":"/private/imagecme/cm020.jpg",
        "branch":"dcme",
        "phonenumber":"9786523412"
    },
    {
        "name":"C shashikumar",
        "pinnumber":"20101-cm-021",
        "firstpayment":"paid",
        "secondpayment":"paid",
        "thirdpayment":"unpaid",
        "amount":"4700/-",
        "photo":"/private/imagecme/cm021.jpg",
        "branch":"dcme",
        "phonenumber":"9786523412"
    },
    {
        "name":"S sreekanth",
        "pinnumber":"20101-cm-022",
        "firstpayment":"paid",
        "secondpayment":"paid",
        "thirdpayment":"unpaid",
        "amount":"4700/-",
        "photo":"/private/imagecme/cm022.jpg",
        "branch":"dcme",
        "phonenumber":"9786523412"
    },
    {
        "name":"s satya priyar",
        "pinnumber":"20101-cm-024",
        "firstpayment":"paid",
        "secondpayment":"paid",
        "thirdpayment":"unpaid",
        "amount":"4700/-",
        "photo":"/private/imagecme/cm024.jpg",
        "branch":"dcme",
        "phonenumber":"9786523412"
    },
    {
        "name":"A tejasree",
        "pinnumber":"20101-cm-025",
        "firstpayment":"paid",
        "secondpayment":"paid",
        "thirdpayment":"unpaid",
        "amount":"4700/-",
        "photo":"/private/imagecme/cm025.jpg",
        "branch":"dcme",
        "phonenumber":"9786523412"
    },
    {
        "name":"R vasuda",
        "pinnumber":"20101-cm-026",
        "firstpayment":"paid",
        "secondpayment":"paid",
        "thirdpayment":"unpaid",
        "amount":"4700/-",
        "photo":"/private/imagecme/cm026.jpg",
        "branch":"dcme",
        "phonenumber":"9786523412"
    },
    {
        "name":"K m anjeenaidu",
        "pinnumber":"20101-cm-027",
        "firstpayment":"paid",
        "secondpayment":"paid",
        "thirdpayment":"unpaid",
        "amount":"4700/-",
        "photo":"/private/imagecme/cm027.jpg",
        "branch":"dcme",
        "phonenumber":"9786523412"
    },
    {
        "name":"M chaitanya",
        "pinnumber":"20101-cm-028",
        "firstpayment":"paid",
        "secondpayment":"paid",
        "thirdpayment":"unpaid",
        "amount":"4700/-",
        "photo":"/private/imagecme/cm028.jpg",
        "branch":"dcme",
        "phonenumber":"9786523412"
    },
    {
        "name":"v danush",
        "pinnumber":"20101-cm-030",
        "firstpayment":"paid",
        "secondpayment":"paid",
        "thirdpayment":"unpaid",
        "amount":"4700/-",
        "photo":"/private/imagecme/cm030.jpg",
        "branch":"dcme",
        "phonenumber":"9786523412"
    }
]